lazy_computing/__init__.py
lazy_computing/lazy.py
lazy_computing-0.1.dist-info/LICENSE
lazy_computing-0.1.dist-info/METADATA
lazy_computing-0.1.dist-info/WHEEL
lazy_computing-0.1.dist-info/top_level.txt
lazy_computing-0.1.dist-info/RECORD
