Metadata-Version: 2.1
Name: lazy-computing
Version: 0.1
Summary: Set of functional and lazy programming tools
Home-page: https://github.com/divad1196/lazy_computing
Author: Gallay David
Author-email: davidtennis96@hotmail.com
License: UNKNOWN
Platform: UNKNOWN
Classifier: Programming Language :: Python :: 3
Classifier: License :: OSI Approved :: MIT License
Classifier: Operating System :: OS Independent
